mssql_scripter-1.0.0a23.data/scripts/mssql-scripter
mssql_scripter-1.0.0a23.data/scripts/mssql-scripter.bat
mssql_scripter-1.0.0a23.dist-info/DESCRIPTION.rst
mssql_scripter-1.0.0a23.dist-info/LICENSE.txt
mssql_scripter-1.0.0a23.dist-info/METADATA
mssql_scripter-1.0.0a23.dist-info/RECORD
mssql_scripter-1.0.0a23.dist-info/WHEEL
mssql_scripter-1.0.0a23.dist-info/metadata.json
mssql_scripter-1.0.0a23.dist-info/top_level.txt
mssql_scripter-1.0.0a23.dist-info/zip-safe
mssqlscripter/__init__.py
mssqlscripter/__main__.py
mssqlscripter/argparser.py
mssqlscripter/main.py
mssqlscripter/scriptercallbacks.py
mssqlscripter/scripterlogging.py
mssqlscripter/sqltoolsclient.py
mssqlscripter/jsonrpc/__init__.py
mssqlscripter/jsonrpc/jsonrpcclient.py
mssqlscripter/jsonrpc/contracts/__init__.py
mssqlscripter/jsonrpc/contracts/scriptingservice.py
mssqlscripter/mssqltoolsservice/__init__.py
mssqlscripter/mssqltoolsservice/external.py
mssqlscripter/mssqltoolsservice/bin/Microsoft.Azure.Management.ResourceManager.dll
mssqlscripter/mssqltoolsservice/bin/Microsoft.Azure.Management.Sql.dll
mssqlscripter/mssqltoolsservice/bin/Microsoft.CSharp.dll
mssqlscripter/mssqltoolsservice/bin/Microsoft.Data.Tools.Sql.BatchParser.dll
mssqlscripter/mssqltoolsservice/bin/Microsoft.DotNet.PlatformAbstractions.dll
mssqlscripter/mssqltoolsservice/bin/Microsoft.Extensions.DependencyModel.dll
mssqlscripter/mssqltoolsservice/bin/Microsoft.Rest.ClientRuntime.Azure.dll
mssqlscripter/mssqltoolsservice/bin/Microsoft.Rest.ClientRuntime.dll
mssqlscripter/mssqltoolsservice/bin/Microsoft.SqlServer.ConnectionInfo.dll
mssqlscripter/mssqltoolsservice/bin/Microsoft.SqlServer.Management.Dmf.dll
mssqlscripter/mssqltoolsservice/bin/Microsoft.SqlServer.Management.Sdk.Sfc.dll
mssqlscripter/mssqltoolsservice/bin/Microsoft.SqlServer.Management.SmoMetadataProvider.dll
mssqlscripter/mssqltoolsservice/bin/Microsoft.SqlServer.Management.SqlScriptPublishModel.dll
mssqlscripter/mssqltoolsservice/bin/Microsoft.SqlServer.Management.XEvent.dll
mssqlscripter/mssqltoolsservice/bin/Microsoft.SqlServer.Management.XEventDbScoped.dll
mssqlscripter/mssqltoolsservice/bin/Microsoft.SqlServer.Management.XEventDbScopedEnum.dll
mssqlscripter/mssqltoolsservice/bin/Microsoft.SqlServer.Management.XEventEnum.dll
mssqlscripter/mssqltoolsservice/bin/Microsoft.SqlServer.Smo.dll
