Metadata-Version: 2.0
Name: mssql-scripter
Version: 1.0.0a23
Summary: Microsoft SQL Scripter Command-Line Tool
Home-page: https://github.com/Microsoft/mssql-scripter/
Author: Microsoft Corporation
Author-email: sqlcli@microsoft.com
License: MIT
Platform: UNKNOWN
Classifier: Development Status :: 3 - Alpha
Classifier: Intended Audience :: Developers
Classifier: Intended Audience :: System Administrators
Classifier: Programming Language :: Python
Classifier: Programming Language :: Python :: 2
Classifier: Programming Language :: Python :: 2.7
Classifier: Programming Language :: Python :: 3
Classifier: Programming Language :: Python :: 3.4
Classifier: Programming Language :: Python :: 3.5
Classifier: Programming Language :: Python :: 3.6
Classifier: License :: OSI Approved :: MIT License
Requires-Dist: future (>=0.16.0)
Requires-Dist: wheel (>=0.29.0)
Requires-Dist: enum34 (>=1.1.6)
